setup.cfg
setup.py
bin/tardocken
tardocken/__init__.py
tardocken.egg-info/PKG-INFO
tardocken.egg-info/SOURCES.txt
tardocken.egg-info/dependency_links.txt
tardocken.egg-info/top_level.txt
tardocken.egg-info/zip-safe