Metadata-Version: 1.0
Name: tardocken
Version: 0.1
Summary: Add extra context to docker builds.
Home-page: https://github.com/KitB/tardocken
Author: Kit Barnes
Author-email: kit@ninjalith.com
License: UNKNOWN
Keywords: docker
Platform: UNKNOWN
